{
  "source_system": "MSC2020",
  "source_url": "https://msc2020.org/MSC_2020.pdf",
  "total_rows_full_scope": 6603,
  "total_rows_core_adjacent": 5533,
  "total_keyword_rows_full_scope": 6603,
  "total_keyword_rows_core_adjacent": 5533,
  "total_unique_keywords_full_scope": 5978,
  "total_unique_keywords_core_adjacent": 5031,
  "sections_included_core_adjacent": [
    "00-XX",
    "03-XX",
    "05-XX",
    "06-XX",
    "08-XX",
    "11-XX",
    "12-XX",
    "13-XX",
    "14-XX",
    "15-XX",
    "16-XX",
    "17-XX",
    "18-XX",
    "19-XX",
    "20-XX",
    "22-XX",
    "26-XX",
    "28-XX",
    "30-XX",
    "31-XX",
    "32-XX",
    "33-XX",
    "34-XX",
    "35-XX",
    "37-XX",
    "39-XX",
    "40-XX",
    "41-XX",
    "42-XX",
    "43-XX",
    "44-XX",
    "45-XX",
    "46-XX",
    "47-XX",
    "49-XX",
    "51-XX",
    "52-XX",
    "53-XX",
    "54-XX",
    "55-XX",
    "57-XX",
    "58-XX",
    "60-XX",
    "62-XX",
    "65-XX",
    "68-XX",
    "90-XX",
    "91-XX",
    "93-XX",
    "94-XX"
  ]
}